ram_romd_design/rom/rom.v
module rom(
    input [4:0] adr,
    input clk,
    input en,
    output reg[4:0] data
);

reg[4:0] mem[32:0];

always @(posedge clk)
begin
  if(en)
  data<=mem[adr];
  else
    data<=5'bxxxxx;
end

initial
 begin
    
  for (integer k=0 ;k<32 ;k=k+1 ) begin
     mem[k]=k;
  end

 end
 
 endmodule

ram_romd_design/rom/rom_tb.v
`timescale 1ns/1ns
`include "rom.v"

module rom_tb;

reg [4:0] adr;
reg clk,en;
wire [4:0] data;

rom r(
    .adr(adr),.clk(clk),.en(en),.data(data)
);

initial 
begin
  $dumpfile("rom_data.vcd");
  $dumpvars(1,rom_tb);

  clk=1'b1;
  forever #5 clk=~clk;
end

initial
 begin
    en=1'b0;
    #12;

    en=1'b1;
    adr=5'b01011;
    #10;

    en=1'b1;
    adr=5'b01000;
    #10;

    en=1'b1;
    adr=5'b01111;
    #10;

    en=1'b1;
    adr=5'b10111;
    #10;

    en=1'b1;
    adr=5'b11011;
    #10;

    en=1'b1;
    adr=5'b00001;
    #10;

    $display("test done");
    #10 $finish;
 end  

endmodule

ram_romd_design/rom/rom_data.vcd
$date
	Mon Jun 24 14:58:40 2024
$end
$version
	Icarus Verilog
$end
$timescale
	1ns
$end
$scope module rom_tb $end
$var wire 5 ! data [4:0] $end
$var reg 5 " adr [4:0] $end
$var reg 1 # clk $end
$var reg 1 $ en $end
$upscope $end
$enddefinitions $end
$comment Show the parameter values. $end
$dumpall
$end
#0
$dumpvars
0$
1#
bx "
bx !
$end
#5
0#
#10
1#
#12
b1011 "
1$
#15
0#
#20
b1011 !
1#
#22
b1000 "
#25
0#
#30
b1000 !
1#
#32
b1111 "
#35
0#
#40
b1111 !
1#
#42
b10111 "
#45
0#
#50
b10111 !
1#
#52
b11011 "
#55
0#
#60
b11011 !
1#
#62
b1 "
#65
0#
#70
b1 !
1#
