ram_romd_design/single_port_ram/single_port_ram.v
module single_port_ram(
input [7:0] data,//input data 8bits
input [5:0] adr,//address location total 2^6=64
input en,
input clk,//enable write and clock
output [7:0] out//output data
);

reg[7:0] ram[63:0]; // 8*64 bit ram
reg[5:0] addres;//address register

always @(posedge clk)
 begin
   if(en)
    ram[adr]<=data;
   else
    addres<=adr;
 end

 assign out=ram[addres];

endmodule

ram_romd_design/single_port_ram/single_port_ram_tb.v
`timescale 1ns / 1ns
`include "single_port_ram.v"

module single_port_ram_tb;

reg[7:0] data;
reg[5:0] adr;
reg en,clk;
wire[7:0] out;

single_port_ram spr(
    .data(data),.adr(adr),.en(en),.clk(clk),.out(out)
);

initial
 begin
  $dumpfile("data.vcd");
  $dumpvars(1,single_port_ram_tb);

  clk=1'b1;
  forever #5 clk=~clk;    
 end

 initial
  begin
   data=8'h01;
   adr=6'b000000;
   en=1'b1;
   #12;

   data=8'h02;
   adr=6'b000001;
   en=1'b1;
   #10;

   data=8'h03;
   adr=6'b000010;
   en=1'b1;
   #10;

  data=8'h04;
   adr=6'b000011;
   en=1'b1;
   #10;

   adr=6'b000010;
   en=1'b0;
   #10;

   adr=6'b000001;
   en=1'b0;
   #10;

  adr=6'b000011;
   en=1'b0;
   #10;

  adr=6'b000000;
   en=1'b0;
   #10;

   $display("test done");
   #10 $finish; 
  end

endmodule

ram_romd_design/single_port_ram/data.vcd
$date
	Mon Jun 24 10:15:36 2024
$end
$version
	Icarus Verilog
$end
$timescale
	1ns
$end
$scope module single_port_ram_tb $end
$var wire 8 ! out [7:0] $end
$var reg 6 " adr [5:0] $end
$var reg 1 # clk $end
$var reg 8 $ data [7:0] $end
$var reg 1 % en $end
$upscope $end
$enddefinitions $end
$comment Show the parameter values. $end
$dumpall
$end
#0
$dumpvars
1%
b1 $
1#
b0 "
bx !
$end
#5
0#
#10
1#
#12
b1 "
b10 $
#15
0#
#20
1#
#22
b10 "
b11 $
#25
0#
#30
1#
#32
b11 "
b100 $
#35
0#
#40
1#
#42
0%
b10 "
#45
0#
#50
b11 !
1#
#52
b1 "
#55
0#
#60
b10 !
1#
#62
b11 "
#65
0#
#70
b100 !
1#
#72
b0 "
#75
0#
#80
b1 !
1#
